MANIFEST.in
README.md
requirements.txt
setup.py
unclegabe/__init__.py
unclegabe/runners.py
unclegabe/settings.py
unclegabe.egg-info/PKG-INFO
unclegabe.egg-info/SOURCES.txt
unclegabe.egg-info/dependency_links.txt
unclegabe.egg-info/not-zip-safe
unclegabe.egg-info/requires.txt
unclegabe.egg-info/top_level.txt